{"timestamp":1570108381172,"name":"beacons-4.0.json","sessions":{"entries":[{"id":1257,"reading":{"timestamp":1570108381382,"avgRssi":-56.82222222222222,"beaconTypeCode":533,"bluetoothName":"lambda","dataFields":[],"distance":0.686533961943955,"extraDataFields":[],"id":"b88a6097e2b6","manufacturer":76,"measurementCount":45,"packetCount":11,"rssi":-56,"runningAverageRssi":-56.82222222222222,"serviceUuid":-1,"txPower":-59,"type":"iBeacon","values":["113069EC-6E64-4BD3-6810-DE01B36E8A3E",1,101],"extraBeaconData":false,"multiFrameBeacon":false}},{"id":1258,"reading":{"timestamp":1570108381384,"avgRssi":-56.82222222222222,"beaconTypeCode":533,"bluetoothName":"lambda","dataFields":[],"distance":0.686533961943955,"extraDataFields":[],"id":"b88a6097e2b6","manufacturer":76,"measurementCount":45,"packetCount":11,"rssi":-56,"runningAverageRssi":-56.82222222222222,"serviceUuid":-1,"txPower":-59,"type":"iBeacon","values":["113069EC-6E64-4BD3-6810-DE01B36E8A3E",1,101],"extraBeaconData":false,"multiFrameBeacon":false}},{"id":1259,"reading":{"timestamp":1570108381386,"avgRssi":-56.82222222222222,"beaconTypeCode":533,"bluetoothName":"lambda","dataFields":[],"distance":0.686533961943955,"extraDataFields":[],"id":"b88a6097e2b6","manufacturer":76,"measurementCount":45,"packetCount":11,"rssi":-56,"runningAverageRssi":-56.82222222222222,"serviceUuid":-1,"txPower":-59,"type":"iBeacon","values":["113069EC-6E64-4BD3-6810-DE01B36E8A3E",1,101],"extraBeaconData":false,"multiFrameBeacon":false}},{"id":1260,"reading":{"timestamp":1570108382492,"avgRssi":-56.86363636363637,"beaconTypeCode":533,"bluetoothName":"lambda","dataFields":[],"distance":0.6915541188426965,"extraDataFields":[],"id":"b88a6097e2b6","manufacturer":76,"measurementCount":44,"packetCount":8,"rssi":-60,"runningAverageRssi":-56.86363636363637,"serviceUuid":-1,"txPower":-59,"type":"iBeacon","values":["113069EC-6E64-4BD3-6810-DE01B36E8A3E",1,101],"extraBeaconData":false,"multiFrameBeacon":false}},{"id":1261,"reading":{"timestamp":1570108382495,"avgRssi":-56.86363636363637,"beaconTypeCode":533,"bluetoothName":"lambda","dataFields":[],"distance":0.6915541188426965,"extraDataFields":[],"id":"b88a6097e2b6","manufacturer":76,"measurementCount":44,"packetCount":8,"rssi":-60,"runningAverageRssi":-56.86363636363637,"serviceUuid":-1,"txPower":-59,"type":"iBeacon","values":["113069EC-6E64-4BD3-6810-DE01B36E8A3E",1,101],"extraBeaconData":false,"multiFrameBeacon":false}},{"id":1262,"reading":{"timestamp":1570108382497,"avgRssi":-56.86363636363637,"beaconTypeCode":533,"bluetoothName":"lambda","dataFields":[],"distance":0.6915541188426965,"extraDataFields":[],"id":"b88a6097e2b6","manufacturer":76,"measurementCount":44,"packetCount":8,"rssi":-60,"runningAverageRssi":-56.86363636363637,"serviceUuid":-1,"txPower":-59,"type":"iBeacon","values":["113069EC-6E64-4BD3-6810-DE01B36E8A3E",1,101],"extraBeaconData":false,"multiFrameBeacon":false}},{"id":1263,"reading":{"timestamp":1570108383594,"avgRssi":-58.395348837209305,"beaconTypeCode":533,"bluetoothName":"lambda","dataFields":[],"distance":0.9021161440381696,"extraDataFields":[],"id":"b88a6097e2b6","manufacturer":76,"measurementCount":43,"packetCount":9,"rssi":-67,"runningAverageRssi":-58.395348837209305,"serviceUuid":-1,"txPower":-59,"type":"iBeacon","values":["113069EC-6E64-4BD3-6810-DE01B36E8A3E",1,101],"extraBeaconData":false,"multiFrameBeacon":false}},{"id":1264,"reading":{"timestamp":1570108383610,"avgRssi":-58.395348837209305,"beaconTypeCode":533,"bluetoothName":"lambda","dataFields":[],"distance":0.9021161440381696,"extraDataFields":[],"id":"b88a6097e2b6","manufacturer":76,"measurementCount":43,"packetCount":9,"rssi":-67,"runningAverageRssi":-58.395348837209305,"serviceUuid":-1,"txPower":-59,"type":"iBeacon","values":["113069EC-6E64-4BD3-6810-DE01B36E8A3E",1,101],"extraBeaconData":false,"multiFrameBeacon":false}},{"id":1265,"reading":{"timestamp":1570108383612,"avgRssi":-58.395348837209305,"beaconTypeCode":533,"bluetoothName":"lambda","dataFields":[],"distance":0.9021161440381696,"extraDataFields":[],"id":"b88a6097e2b6","manufacturer":76,"measurementCount":43,"packetCount":9,"rssi":-67,"runningAverageRssi":-58.395348837209305,"serviceUuid":-1,"txPower":-59,"type":"iBeacon","values":["113069EC-6E64-4BD3-6810-DE01B36E8A3E",1,101],"extraBeaconData":false,"multiFrameBeacon":false}},{"id":1266,"reading":{"timestamp":1570108384698,"avgRssi":-60.09756097560975,"beaconTypeCode":533,"bluetoothName":"lambda","dataFields":[],"distance":1.028356463930276,"extraDataFields":[],"id":"b88a6097e2b6","manufacturer":76,"measurementCount":41,"packetCount":9,"rssi":-62,"runningAverageRssi":-60.09756097560975,"serviceUuid":-1,"txPower":-59,"type":"iBeacon","values":["113069EC-6E64-4BD3-6810-DE01B36E8A3E",1,101],"extraBeaconData":false,"multiFrameBeacon":false}},{"id":1267,"reading":{"timestamp":1570108384713,"avgRssi":-60.09756097560975,"beaconTypeCode":533,"bluetoothName":"lambda","dataFields":[],"distance":1.028356463930276,"extraDataFields":[],"id":"b88a6097e2b6","manufacturer":76,"measurementCount":41,"packetCount":9,"rssi":-62,"runningAverageRssi":-60.09756097560975,"serviceUuid":-1,"txPower":-59,"type":"iBeacon","values":["113069EC-6E64-4BD3-6810-DE01B36E8A3E",1,101],"extraBeaconData":false,"multiFrameBeacon":false}},{"id":1268,"reading":{"timestamp":1570108384715,"avgRssi":-60.09756097560975,"beaconTypeCode":533,"bluetoothName":"lambda","dataFields":[],"distance":1.028356463930276,"extraDataFields":[],"id":"b88a6097e2b6","manufacturer":76,"measurementCount":41,"packetCount":9,"rssi":-62,"runningAverageRssi":-60.09756097560975,"serviceUuid":-1,"txPower":-59,"type":"iBeacon","values":["113069EC-6E64-4BD3-6810-DE01B36E8A3E",1,101],"extraBeaconData":false,"multiFrameBeacon":false}},{"id":1269,"reading":{"timestamp":1570108385799,"avgRssi":-62.214285714285715,"beaconTypeCode":533,"bluetoothName":"lambda","dataFields":[],"distance":1.158432405319327,"extraDataFields":[],"id":"b88a6097e2b6","manufacturer":76,"measurementCount":42,"packetCount":10,"rssi":-66,"runningAverageRssi":-62.214285714285715,"serviceUuid":-1,"txPower":-59,"type":"iBeacon","values":["113069EC-6E64-4BD3-6810-DE01B36E8A3E",1,101],"extraBeaconData":false,"multiFrameBeacon":false}},{"id":1270,"reading":{"timestamp":1570108385802,"avgRssi":-62.214285714285715,"beaconTypeCode":533,"bluetoothName":"lambda","dataFields":[],"distance":1.158432405319327,"extraDataFields":[],"id":"b88a6097e2b6","manufacturer":76,"measurementCount":42,"packetCount":10,"rssi":-66,"runningAverageRssi":-62.214285714285715,"serviceUuid":-1,"txPower":-59,"type":"iBeacon","values":["113069EC-6E64-4BD3-6810-DE01B36E8A3E",1,101],"extraBeaconData":false,"multiFrameBeacon":false}},{"id":1271,"reading":{"timestamp":1570108385803,"avgRssi":-62.214285714285715,"beaconTypeCode":533,"bluetoothName":"lambda","dataFields":[],"distance":1.158432405319327,"extraDataFields":[],"id":"b88a6097e2b6","manufacturer":76,"measurementCount":42,"packetCount":10,"rssi":-66,"runningAverageRssi":-62.214285714285715,"serviceUuid":-1,"txPower":-59,"type":"iBeacon","values":["113069EC-6E64-4BD3-6810-DE01B36E8A3E",1,101],"extraBeaconData":false,"multiFrameBeacon":false}},{"id":1272,"reading":{"timestamp":1570108386904,"avgRssi":-63.78048780487805,"beaconTypeCode":533,"bluetoothName":"lambda","dataFields":[],"distance":1.273168690534031,"extraDataFields":[],"id":"b88a6097e2b6","manufacturer":76,"measurementCount":41,"packetCount":8,"rssi":-58,"runningAverageRssi":-63.78048780487805,"serviceUuid":-1,"txPower":-59,"type":"iBeacon","values":["113069EC-6E64-4BD3-6810-DE01B36E8A3E",1,101],"extraBeaconData":false,"multiFrameBeacon":false}},{"id":1273,"reading":{"timestamp":1570108386907,"avgRssi":-63.78048780487805,"beaconTypeCode":533,"bluetoothName":"lambda","dataFields":[],"distance":1.273168690534031,"extraDataFields":[],"id":"b88a6097e2b6","manufacturer":76,"measurementCount":41,"packetCount":8,"rssi":-58,"runningAverageRssi":-63.78048780487805,"serviceUuid":-1,"txPower":-59,"type":"iBeacon","values":["113069EC-6E64-4BD3-6810-DE01B36E8A3E",1,101],"extraBeaconData":false,"multiFrameBeacon":false}},{"id":1274,"reading":{"timestamp":1570108386909,"avgRssi":-63.78048780487805,"beaconTypeCode":533,"bluetoothName":"lambda","dataFields":[],"distance":1.273168690534031,"extraDataFields":[],"id":"b88a6097e2b6","manufacturer":76,"measurementCount":41,"packetCount":8,"rssi":-58,"runningAverageRssi":-63.78048780487805,"serviceUuid":-1,"txPower":-59,"type":"iBeacon","values":["113069EC-6E64-4BD3-6810-DE01B36E8A3E",1,101],"extraBeaconData":false,"multiFrameBeacon":false}},{"id":1275,"reading":{"timestamp":1570108388010,"avgRssi":-63.55,"beaconTypeCode":533,"bluetoothName":"lambda","dataFields":[],"distance":1.2552040662911077,"extraDataFields":[],"id":"b88a6097e2b6","manufacturer":76,"measurementCount":40,"packetCount":8,"rssi":-58,"runningAverageRssi":-63.55,"serviceUuid":-1,"txPower":-59,"type":"iBeacon","values":["113069EC-6E64-4BD3-6810-DE01B36E8A3E",1,101],"extraBeaconData":false,"multiFrameBeacon":false}},{"id":1276,"reading":{"timestamp":1570108388013,"avgRssi":-63.55,"beaconTypeCode":533,"bluetoothName":"lambda","dataFields":[],"distance":1.2552040662911077,"extraDataFields":[],"id":"b88a6097e2b6","manufacturer":76,"measurementCount":40,"packetCount":8,"rssi":-58,"runningAverageRssi":-63.55,"serviceUuid":-1,"txPower":-59,"type":"iBeacon","values":["113069EC-6E64-4BD3-6810-DE01B36E8A3E",1,101],"extraBeaconData":false,"multiFrameBeacon":false}},{"id":1277,"reading":{"timestamp":1570108388041,"avgRssi":-63.55,"beaconTypeCode":533,"bluetoothName":"lambda","dataFields":[],"distance":1.2552040662911077,"extraDataFields":[],"id":"b88a6097e2b6","manufacturer":76,"measurementCount":40,"packetCount":8,"rssi":-58,"runningAverageRssi":-63.55,"serviceUuid":-1,"txPower":-59,"type":"iBeacon","values":["113069EC-6E64-4BD3-6810-DE01B36E8A3E",1,101],"extraBeaconData":false,"multiFrameBeacon":false}},{"id":1278,"reading":{"timestamp":1570108389110,"avgRssi":-61.794871794871796,"beaconTypeCode":533,"bluetoothName":"lambda","dataFields":[],"distance":1.1304966758847135,"extraDataFields":[],"id":"b88a6097e2b6","manufacturer":76,"measurementCount":39,"packetCount":9,"rssi":-58,"runningAverageRssi":-61.794871794871796,"serviceUuid":-1,"txPower":-59,"type":"iBeacon","values":["113069EC-6E64-4BD3-6810-DE01B36E8A3E",1,101],"extraBeaconData":false,"multiFrameBeacon":false}},{"id":1279,"reading":{"timestamp":1570108389112,"avgRssi":-61.794871794871796,"beaconTypeCode":533,"bluetoothName":"lambda","dataFields":[],"distance":1.1304966758847135,"extraDataFields":[],"id":"b88a6097e2b6","manufacturer":76,"measurementCount":39,"packetCount":9,"rssi":-58,"runningAverageRssi":-61.794871794871796,"serviceUuid":-1,"txPower":-59,"type":"iBeacon","values":["113069EC-6E64-4BD3-6810-DE01B36E8A3E",1,101],"extraBeaconData":false,"multiFrameBeacon":false}},{"id":1280,"reading":{"timestamp":1570108389112,"avgRssi":-61.794871794871796,"beaconTypeCode":533,"bluetoothName":"lambda","dataFields":[],"distance":1.1304966758847135,"extraDataFields":[],"id":"b88a6097e2b6","manufacturer":76,"measurementCount":39,"packetCount":9,"rssi":-58,"runningAverageRssi":-61.794871794871796,"serviceUuid":-1,"txPower":-59,"type":"iBeacon","values":["113069EC-6E64-4BD3-6810-DE01B36E8A3E",1,101],"extraBeaconData":false,"multiFrameBeacon":false}},{"id":1281,"reading":{"timestamp":1570108390215,"avgRssi":-60.07692307692308,"beaconTypeCode":533,"bluetoothName":"lambda","dataFields":[],"distance":1.0272161505476922,"extraDataFields":[],"id":"b88a6097e2b6","manufacturer":76,"measurementCount":39,"packetCount":9,"rssi":-58,"runningAverageRssi":-60.07692307692308,"serviceUuid":-1,"txPower":-59,"type":"iBeacon","values":["113069EC-6E64-4BD3-6810-DE01B36E8A3E",1,101],"extraBeaconData":false,"multiFrameBeacon":false}},{"id":1282,"reading":{"timestamp":1570108390219,"avgRssi":-60.07692307692308,"beaconTypeCode":533,"bluetoothName":"lambda","dataFields":[],"distance":1.0272161505476922,"extraDataFields":[],"id":"b88a6097e2b6","manufacturer":76,"measurementCount":39,"packetCount":9,"rssi":-58,"runningAverageRssi":-60.07692307692308,"serviceUuid":-1,"txPower":-59,"type":"iBeacon","values":["113069EC-6E64-4BD3-6810-DE01B36E8A3E",1,101],"extraBeaconData":false,"multiFrameBeacon":false}},{"id":1283,"reading":{"timestamp":1570108390221,"avgRssi":-60.07692307692308,"beaconTypeCode":533,"bluetoothName":"lambda","dataFields":[],"distance":1.0272161505476922,"extraDataFields":[],"id":"b88a6097e2b6","manufacturer":76,"measurementCount":39,"packetCount":9,"rssi":-58,"runningAverageRssi":-60.07692307692308,"serviceUuid":-1,"txPower":-59,"type":"iBeacon","values":["113069EC-6E64-4BD3-6810-DE01B36E8A3E",1,101],"extraBeaconData":false,"multiFrameBeacon":false}},{"id":1284,"reading":{"timestamp":1570108391320,"avgRssi":-58.75675675675676,"beaconTypeCode":533,"bluetoothName":"lambda","dataFields":[],"distance":0.959528857249145,"extraDataFields":[],"id":"b88a6097e2b6","manufacturer":76,"measurementCount":37,"packetCount":6,"rssi":-60,"runningAverageRssi":-58.75675675675676,"serviceUuid":-1,"txPower":-59,"type":"iBeacon","values":["113069EC-6E64-4BD3-6810-DE01B36E8A3E",1,101],"extraBeaconData":false,"multiFrameBeacon":false}},{"id":1285,"reading":{"timestamp":1570108391323,"avgRssi":-58.75675675675676,"beaconTypeCode":533,"bluetoothName":"lambda","dataFields":[],"distance":0.959528857249145,"extraDataFields":[],"id":"b88a6097e2b6","manufacturer":76,"measurementCount":37,"packetCount":6,"rssi":-60,"runningAverageRssi":-58.75675675675676,"serviceUuid":-1,"txPower":-59,"type":"iBeacon","values":["113069EC-6E64-4BD3-6810-DE01B36E8A3E",1,101],"extraBeaconData":false,"multiFrameBeacon":false}},{"id":1286,"reading":{"timestamp":1570108391325,"avgRssi":-58.75675675675676,"beaconTypeCode":533,"bluetoothName":"lambda","dataFields":[],"distance":0.959528857249145,"extraDataFields":[],"id":"b88a6097e2b6","manufacturer":76,"measurementCount":37,"packetCount":6,"rssi":-60,"runningAverageRssi":-58.75675675675676,"serviceUuid":-1,"txPower":-59,"type":"iBeacon","values":["113069EC-6E64-4BD3-6810-DE01B36E8A3E",1,101],"extraBeaconData":false,"multiFrameBeacon":false}},{"id":1287,"reading":{"timestamp":1570108395749,"avgRssi":-67.0,"beaconTypeCode":533,"bluetoothName":"lambda","dataFields":[],"distance":1.5682199970445823,"extraDataFields":[],"id":"b88a6097e2b6","manufacturer":76,"measurementCount":6,"packetCount":5,"rssi":-66,"runningAverageRssi":-67.0,"serviceUuid":-1,"txPower":-59,"type":"iBeacon","values":["113069EC-6E64-4BD3-6810-DE01B36E8A3E",1,101],"extraBeaconData":false,"multiFrameBeacon":false}},{"id":1288,"reading":{"timestamp":1570108395752,"avgRssi":-67.0,"beaconTypeCode":533,"bluetoothName":"lambda","dataFields":[],"distance":1.5682199970445823,"extraDataFields":[],"id":"b88a6097e2b6","manufacturer":76,"measurementCount":6,"packetCount":5,"rssi":-66,"runningAverageRssi":-67.0,"serviceUuid":-1,"txPower":-59,"type":"iBeacon","values":["113069EC-6E64-4BD3-6810-DE01B36E8A3E",1,101],"extraBeaconData":false,"multiFrameBeacon":false}},{"id":1289,"reading":{"timestamp":1570108395766,"avgRssi":-67.0,"beaconTypeCode":533,"bluetoothName":"lambda","dataFields":[],"distance":1.5682199970445823,"extraDataFields":[],"id":"b88a6097e2b6","manufacturer":76,"measurementCount":6,"packetCount":5,"rssi":-66,"runningAverageRssi":-67.0,"serviceUuid":-1,"txPower":-59,"type":"iBeacon","values":["113069EC-6E64-4BD3-6810-DE01B36E8A3E",1,101],"extraBeaconData":false,"multiFrameBeacon":false}},{"id":1290,"reading":{"timestamp":1570108396848,"avgRssi":-66.46153846153847,"beaconTypeCode":533,"bluetoothName":"lambda","dataFields":[],"distance":1.5127031612845778,"extraDataFields":[],"id":"b88a6097e2b6","manufacturer":76,"measurementCount":13,"packetCount":8,"rssi":-64,"runningAverageRssi":-66.46153846153847,"serviceUuid":-1,"txPower":-59,"type":"iBeacon","values":["113069EC-6E64-4BD3-6810-DE01B36E8A3E",1,101],"extraBeaconData":false,"multiFrameBeacon":false}},{"id":1291,"reading":{"timestamp":1570108396851,"avgRssi":-66.46153846153847,"beaconTypeCode":533,"bluetoothName":"lambda","dataFields":[],"distance":1.5127031612845778,"extraDataFields":[],"id":"b88a6097e2b6","manufacturer":76,"measurementCount":13,"packetCount":8,"rssi":-64,"runningAverageRssi":-66.46153846153847,"serviceUuid":-1,"txPower":-59,"type":"iBeacon","values":["113069EC-6E64-4BD3-6810-DE01B36E8A3E",1,101],"extraBeaconData":false,"multiFrameBeacon":false}},{"id":1292,"reading":{"timestamp":1570108396852,"avgRssi":-66.46153846153847,"beaconTypeCode":533,"bluetoothName":"lambda","dataFields":[],"distance":1.5127031612845778,"extraDataFields":[],"id":"b88a6097e2b6","manufacturer":76,"measurementCount":13,"packetCount":8,"rssi":-64,"runningAverageRssi":-66.46153846153847,"serviceUuid":-1,"txPower":-59,"type":"iBeacon","values":["113069EC-6E64-4BD3-6810-DE01B36E8A3E",1,101],"extraBeaconData":false,"multiFrameBeacon":false}},{"id":1293,"reading":{"timestamp":1570108397952,"avgRssi":-66.04545454545455,"beaconTypeCode":533,"bluetoothName":"lambda","dataFields":[],"distance":1.4715979716919336,"extraDataFields":[],"id":"b88a6097e2b6","manufacturer":76,"measurementCount":22,"packetCount":9,"rssi":-65,"runningAverageRssi":-66.04545454545455,"serviceUuid":-1,"txPower":-59,"type":"iBeacon","values":["113069EC-6E64-4BD3-6810-DE01B36E8A3E",1,101],"extraBeaconData":false,"multiFrameBeacon":false}},{"id":1294,"reading":{"timestamp":1570108397955,"avgRssi":-66.04545454545455,"beaconTypeCode":533,"bluetoothName":"lambda","dataFields":[],"distance":1.4715979716919336,"extraDataFields":[],"id":"b88a6097e2b6","manufacturer":76,"measurementCount":22,"packetCount":9,"rssi":-65,"runningAverageRssi":-66.04545454545455,"serviceUuid":-1,"txPower":-59,"type":"iBeacon","values":["113069EC-6E64-4BD3-6810-DE01B36E8A3E",1,101],"extraBeaconData":false,"multiFrameBeacon":false}},{"id":1295,"reading":{"timestamp":1570108397957,"avgRssi":-66.04545454545455,"beaconTypeCode":533,"bluetoothName":"lambda","dataFields":[],"distance":1.4715979716919336,"extraDataFields":[],"id":"b88a6097e2b6","manufacturer":76,"measurementCount":22,"packetCount":9,"rssi":-65,"runningAverageRssi":-66.04545454545455,"serviceUuid":-1,"txPower":-59,"type":"iBeacon","values":["113069EC-6E64-4BD3-6810-DE01B36E8A3E",1,101],"extraBeaconData":false,"multiFrameBeacon":false}},{"id":1296,"reading":{"timestamp":1570108399052,"avgRssi":-65.74193548387096,"beaconTypeCode":533,"bluetoothName":"lambda","dataFields":[],"distance":1.442569359819449,"extraDataFields":[],"id":"b88a6097e2b6","manufacturer":76,"measurementCount":31,"packetCount":9,"rssi":-65,"runningAverageRssi":-65.74193548387096,"serviceUuid":-1,"txPower":-59,"type":"iBeacon","values":["113069EC-6E64-4BD3-6810-DE01B36E8A3E",1,101],"extraBeaconData":false,"multiFrameBeacon":false}},{"id":1297,"reading":{"timestamp":1570108399055,"avgRssi":-65.74193548387096,"beaconTypeCode":533,"bluetoothName":"lambda","dataFields":[],"distance":1.442569359819449,"extraDataFields":[],"id":"b88a6097e2b6","manufacturer":76,"measurementCount":31,"packetCount":9,"rssi":-65,"runningAverageRssi":-65.74193548387096,"serviceUuid":-1,"txPower":-59,"type":"iBeacon","values":["113069EC-6E64-4BD3-6810-DE01B36E8A3E",1,101],"extraBeaconData":false,"multiFrameBeacon":false}},{"id":1298,"reading":{"timestamp":1570108399071,"avgRssi":-65.74193548387096,"beaconTypeCode":533,"bluetoothName":"lambda","dataFields":[],"distance":1.442569359819449,"extraDataFields":[],"id":"b88a6097e2b6","manufacturer":76,"measurementCount":31,"packetCount":9,"rssi":-65,"runningAverageRssi":-65.74193548387096,"serviceUuid":-1,"txPower":-59,"type":"iBeacon","values":["113069EC-6E64-4BD3-6810-DE01B36E8A3E",1,101],"extraBeaconData":false,"multiFrameBeacon":false}},{"id":1299,"reading":{"timestamp":1570108400156,"avgRssi":-63.4,"beaconTypeCode":533,"bluetoothName":"lambda","dataFields":[],"distance":1.2437191625989104,"extraDataFields":[],"id":"b88a6097e2b6","manufacturer":76,"measurementCount":40,"packetCount":10,"rssi":-57,"runningAverageRssi":-63.4,"serviceUuid":-1,"txPower":-59,"type":"iBeacon","values":["113069EC-6E64-4BD3-6810-DE01B36E8A3E",1,101],"extraBeaconData":false,"multiFrameBeacon":false}},{"id":1300,"reading":{"timestamp":1570108400159,"avgRssi":-63.4,"beaconTypeCode":533,"bluetoothName":"lambda","dataFields":[],"distance":1.2437191625989104,"extraDataFields":[],"id":"b88a6097e2b6","manufacturer":76,"measurementCount":40,"packetCount":10,"rssi":-57,"runningAverageRssi":-63.4,"serviceUuid":-1,"txPower":-59,"type":"iBeacon","values":["113069EC-6E64-4BD3-6810-DE01B36E8A3E",1,101],"extraBeaconData":false,"multiFrameBeacon":false}},{"id":1301,"reading":{"timestamp":1570108400174,"avgRssi":-63.4,"beaconTypeCode":533,"bluetoothName":"lambda","dataFields":[],"distance":1.2437191625989104,"extraDataFields":[],"id":"b88a6097e2b6","manufacturer":76,"measurementCount":40,"packetCount":10,"rssi":-57,"runningAverageRssi":-63.4,"serviceUuid":-1,"txPower":-59,"type":"iBeacon","values":["113069EC-6E64-4BD3-6810-DE01B36E8A3E",1,101],"extraBeaconData":false,"multiFrameBeacon":false}},{"id":1302,"reading":{"timestamp":1570108401262,"avgRssi":-61.609756097560975,"beaconTypeCode":533,"bluetoothName":"lambda","dataFields":[],"distance":1.118520499028277,"extraDataFields":[],"id":"b88a6097e2b6","manufacturer":76,"measurementCount":41,"packetCount":9,"rssi":-57,"runningAverageRssi":-61.609756097560975,"serviceUuid":-1,"txPower":-59,"type":"iBeacon","values":["113069EC-6E64-4BD3-6810-DE01B36E8A3E",1,101],"extraBeaconData":false,"multiFrameBeacon":false}},{"id":1303,"reading":{"timestamp":1570108401265,"avgRssi":-61.609756097560975,"beaconTypeCode":533,"bluetoothName":"lambda","dataFields":[],"distance":1.118520499028277,"extraDataFields":[],"id":"b88a6097e2b6","manufacturer":76,"measurementCount":41,"packetCount":9,"rssi":-57,"runningAverageRssi":-61.609756097560975,"serviceUuid":-1,"txPower":-59,"type":"iBeacon","values":["113069EC-6E64-4BD3-6810-DE01B36E8A3E",1,101],"extraBeaconData":false,"multiFrameBeacon":false}},{"id":1304,"reading":{"timestamp":1570108401267,"avgRssi":-61.609756097560975,"beaconTypeCode":533,"bluetoothName":"lambda","dataFields":[],"distance":1.118520499028277,"extraDataFields":[],"id":"b88a6097e2b6","manufacturer":76,"measurementCount":41,"packetCount":9,"rssi":-57,"runningAverageRssi":-61.609756097560975,"serviceUuid":-1,"txPower":-59,"type":"iBeacon","values":["113069EC-6E64-4BD3-6810-DE01B36E8A3E",1,101],"extraBeaconData":false,"multiFrameBeacon":false}},{"id":1305,"reading":{"timestamp":1570108402371,"avgRssi":-60.025,"beaconTypeCode":533,"bluetoothName":"lambda","dataFields":[],"distance":1.0243575108752678,"extraDataFields":[],"id":"b88a6097e2b6","manufacturer":76,"measurementCount":40,"packetCount":8,"rssi":-58,"runningAverageRssi":-60.025,"serviceUuid":-1,"txPower":-59,"type":"iBeacon","values":["113069EC-6E64-4BD3-6810-DE01B36E8A3E",1,101],"extraBeaconData":false,"multiFrameBeacon":false}},{"id":1306,"reading":{"timestamp":1570108402374,"avgRssi":-60.025,"beaconTypeCode":533,"bluetoothName":"lambda","dataFields":[],"distance":1.0243575108752678,"extraDataFields":[],"id":"b88a6097e2b6","manufacturer":76,"measurementCount":40,"packetCount":8,"rssi":-58,"runningAverageRssi":-60.025,"serviceUuid":-1,"txPower":-59,"type":"iBeacon","values":["113069EC-6E64-4BD3-6810-DE01B36E8A3E",1,101],"extraBeaconData":false,"multiFrameBeacon":false}},{"id":1307,"reading":{"timestamp":1570108402376,"avgRssi":-60.025,"beaconTypeCode":533,"bluetoothName":"lambda","dataFields":[],"distance":1.0243575108752678,"extraDataFields":[],"id":"b88a6097e2b6","manufacturer":76,"measurementCount":40,"packetCount":8,"rssi":-58,"runningAverageRssi":-60.025,"serviceUuid":-1,"txPower":-59,"type":"iBeacon","values":["113069EC-6E64-4BD3-6810-DE01B36E8A3E",1,101],"extraBeaconData":false,"multiFrameBeacon":false}},{"id":1308,"reading":{"timestamp":1570108403472,"avgRssi":-58.57142857142857,"beaconTypeCode":533,"bluetoothName":"lambda","dataFields":[],"distance":0.9296897667494355,"extraDataFields":[],"id":"b88a6097e2b6","manufacturer":76,"measurementCount":42,"packetCount":10,"rssi":-58,"runningAverageRssi":-58.57142857142857,"serviceUuid":-1,"txPower":-59,"type":"iBeacon","values":["113069EC-6E64-4BD3-6810-DE01B36E8A3E",1,101],"extraBeaconData":false,"multiFrameBeacon":false}},{"id":1309,"reading":{"timestamp":1570108403475,"avgRssi":-58.57142857142857,"beaconTypeCode":533,"bluetoothName":"lambda","dataFields":[],"distance":0.9296897667494355,"extraDataFields":[],"id":"b88a6097e2b6","manufacturer":76,"measurementCount":42,"packetCount":10,"rssi":-58,"runningAverageRssi":-58.57142857142857,"serviceUuid":-1,"txPower":-59,"type":"iBeacon","values":["113069EC-6E64-4BD3-6810-DE01B36E8A3E",1,101],"extraBeaconData":false,"multiFrameBeacon":false}},{"id":1310,"reading":{"timestamp":1570108403477,"avgRssi":-58.57142857142857,"beaconTypeCode":533,"bluetoothName":"lambda","dataFields":[],"distance":0.9296897667494355,"extraDataFields":[],"id":"b88a6097e2b6","manufacturer":76,"measurementCount":42,"packetCount":10,"rssi":-58,"runningAverageRssi":-58.57142857142857,"serviceUuid":-1,"txPower":-59,"type":"iBeacon","values":["113069EC-6E64-4BD3-6810-DE01B36E8A3E",1,101],"extraBeaconData":false,"multiFrameBeacon":false}},{"id":1311,"reading":{"timestamp":1570108404576,"avgRssi":-57.69230769230769,"beaconTypeCode":533,"bluetoothName":"lambda","dataFields":[],"distance":0.7992064761666506,"extraDataFields":[],"id":"b88a6097e2b6","manufacturer":76,"measurementCount":39,"packetCount":7,"rssi":-58,"runningAverageRssi":-57.69230769230769,"serviceUuid":-1,"txPower":-59,"type":"iBeacon","values":["113069EC-6E64-4BD3-6810-DE01B36E8A3E",1,101],"extraBeaconData":false,"multiFrameBeacon":false}},{"id":1312,"reading":{"timestamp":1570108404580,"avgRssi":-57.69230769230769,"beaconTypeCode":533,"bluetoothName":"lambda","dataFields":[],"distance":0.7992064761666506,"extraDataFields":[],"id":"b88a6097e2b6","manufacturer":76,"measurementCount":39,"packetCount":7,"rssi":-58,"runningAverageRssi":-57.69230769230769,"serviceUuid":-1,"txPower":-59,"type":"iBeacon","values":["113069EC-6E64-4BD3-6810-DE01B36E8A3E",1,101],"extraBeaconData":false,"multiFrameBeacon":false}},{"id":1313,"reading":{"timestamp":1570108404582,"avgRssi":-57.69230769230769,"beaconTypeCode":533,"bluetoothName":"lambda","dataFields":[],"distance":0.7992064761666506,"extraDataFields":[],"id":"b88a6097e2b6","manufacturer":76,"measurementCount":39,"packetCount":7,"rssi":-58,"runningAverageRssi":-57.69230769230769,"serviceUuid":-1,"txPower":-59,"type":"iBeacon","values":["113069EC-6E64-4BD3-6810-DE01B36E8A3E",1,101],"extraBeaconData":false,"multiFrameBeacon":false}},{"id":1314,"reading":{"timestamp":1570108405682,"avgRssi":-57.951219512195124,"beaconTypeCode":533,"bluetoothName":"lambda","dataFields":[],"distance":0.8358063752504625,"extraDataFields":[],"id":"b88a6097e2b6","manufacturer":76,"measurementCount":41,"packetCount":11,"rssi":-58,"runningAverageRssi":-57.951219512195124,"serviceUuid":-1,"txPower":-59,"type":"iBeacon","values":["113069EC-6E64-4BD3-6810-DE01B36E8A3E",1,101],"extraBeaconData":false,"multiFrameBeacon":false}},{"id":1315,"reading":{"timestamp":1570108405685,"avgRssi":-57.951219512195124,"beaconTypeCode":533,"bluetoothName":"lambda","dataFields":[],"distance":0.8358063752504625,"extraDataFields":[],"id":"b88a6097e2b6","manufacturer":76,"measurementCount":41,"packetCount":11,"rssi":-58,"runningAverageRssi":-57.951219512195124,"serviceUuid":-1,"txPower":-59,"type":"iBeacon","values":["113069EC-6E64-4BD3-6810-DE01B36E8A3E",1,101],"extraBeaconData":false,"multiFrameBeacon":false}},{"id":1316,"reading":{"timestamp":1570108405687,"avgRssi":-57.951219512195124,"beaconTypeCode":533,"bluetoothName":"lambda","dataFields":[],"distance":0.8358063752504625,"extraDataFields":[],"id":"b88a6097e2b6","manufacturer":76,"measurementCount":41,"packetCount":11,"rssi":-58,"runningAverageRssi":-57.951219512195124,"serviceUuid":-1,"txPower":-59,"type":"iBeacon","values":["113069EC-6E64-4BD3-6810-DE01B36E8A3E",1,101],"extraBeaconData":false,"multiFrameBeacon":false}},{"id":1317,"reading":{"timestamp":1570108406788,"avgRssi":-58.02564102564103,"beaconTypeCode":533,"bluetoothName":"lambda","dataFields":[],"distance":0.8466021223247536,"extraDataFields":[],"id":"b88a6097e2b6","manufacturer":76,"measurementCount":39,"packetCount":8,"rssi":-59,"runningAverageRssi":-58.02564102564103,"serviceUuid":-1,"txPower":-59,"type":"iBeacon","values":["113069EC-6E64-4BD3-6810-DE01B36E8A3E",1,101],"extraBeaconData":false,"multiFrameBeacon":false}},{"id":1318,"reading":{"timestamp":1570108406792,"avgRssi":-58.02564102564103,"beaconTypeCode":533,"bluetoothName":"lambda","dataFields":[],"distance":0.8466021223247536,"extraDataFields":[],"id":"b88a6097e2b6","manufacturer":76,"measurementCount":39,"packetCount":8,"rssi":-59,"runningAverageRssi":-58.02564102564103,"serviceUuid":-1,"txPower":-59,"type":"iBeacon","values":["113069EC-6E64-4BD3-6810-DE01B36E8A3E",1,101],"extraBeaconData":false,"multiFrameBeacon":false}},{"id":1319,"reading":{"timestamp":1570108406794,"avgRssi":-58.02564102564103,"beaconTypeCode":533,"bluetoothName":"lambda","dataFields":[],"distance":0.8466021223247536,"extraDataFields":[],"id":"b88a6097e2b6","manufacturer":76,"measurementCount":39,"packetCount":8,"rssi":-59,"runningAverageRssi":-58.02564102564103,"serviceUuid":-1,"txPower":-59,"type":"iBeacon","values":["113069EC-6E64-4BD3-6810-DE01B36E8A3E",1,101],"extraBeaconData":false,"multiFrameBeacon":false}},{"id":1320,"reading":{"timestamp":1570108407892,"avgRssi":-59.0,"beaconTypeCode":533,"bluetoothName":"lambda","dataFields":[],"distance":0.97085,"extraDataFields":[],"id":"b88a6097e2b6","manufacturer":76,"measurementCount":41,"packetCount":10,"rssi":-64,"runningAverageRssi":-59.0,"serviceUuid":-1,"txPower":-59,"type":"iBeacon","values":["113069EC-6E64-4BD3-6810-DE01B36E8A3E",1,101],"extraBeaconData":false,"multiFrameBeacon":false}},{"id":1321,"reading":{"timestamp":1570108407896,"avgRssi":-59.0,"beaconTypeCode":533,"bluetoothName":"lambda","dataFields":[],"distance":0.97085,"extraDataFields":[],"id":"b88a6097e2b6","manufacturer":76,"measurementCount":41,"packetCount":10,"rssi":-64,"runningAverageRssi":-59.0,"serviceUuid":-1,"txPower":-59,"type":"iBeacon","values":["113069EC-6E64-4BD3-6810-DE01B36E8A3E",1,101],"extraBeaconData":false,"multiFrameBeacon":false}},{"id":1322,"reading":{"timestamp":1570108407898,"avgRssi":-59.0,"beaconTypeCode":533,"bluetoothName":"lambda","dataFields":[],"distance":0.97085,"extraDataFields":[],"id":"b88a6097e2b6","manufacturer":76,"measurementCount":41,"packetCount":10,"rssi":-64,"runningAverageRssi":-59.0,"serviceUuid":-1,"txPower":-59,"type":"iBeacon","values":["113069EC-6E64-4BD3-6810-DE01B36E8A3E",1,101],"extraBeaconData":false,"multiFrameBeacon":false}},{"id":1323,"reading":{"timestamp":1570108408995,"avgRssi":-60.095238095238095,"beaconTypeCode":533,"bluetoothName":"lambda","dataFields":[],"distance":1.0282280006057165,"extraDataFields":[],"id":"b88a6097e2b6","manufacturer":76,"measurementCount":42,"packetCount":9,"rssi":-63,"runningAverageRssi":-60.095238095238095,"serviceUuid":-1,"txPower":-59,"type":"iBeacon","values":["113069EC-6E64-4BD3-6810-DE01B36E8A3E",1,101],"extraBeaconData":false,"multiFrameBeacon":false}},{"id":1324,"reading":{"timestamp":1570108408998,"avgRssi":-60.095238095238095,"beaconTypeCode":533,"bluetoothName":"lambda","dataFields":[],"distance":1.0282280006057165,"extraDataFields":[],"id":"b88a6097e2b6","manufacturer":76,"measurementCount":42,"packetCount":9,"rssi":-63,"runningAverageRssi":-60.095238095238095,"serviceUuid":-1,"txPower":-59,"type":"iBeacon","values":["113069EC-6E64-4BD3-6810-DE01B36E8A3E",1,101],"extraBeaconData":false,"multiFrameBeacon":false}},{"id":1325,"reading":{"timestamp":1570108409000,"avgRssi":-60.095238095238095,"beaconTypeCode":533,"bluetoothName":"lambda","dataFields":[],"distance":1.0282280006057165,"extraDataFields":[],"id":"b88a6097e2b6","manufacturer":76,"measurementCount":42,"packetCount":9,"rssi":-63,"runningAverageRssi":-60.095238095238095,"serviceUuid":-1,"txPower":-59,"type":"iBeacon","values":["113069EC-6E64-4BD3-6810-DE01B36E8A3E",1,101],"extraBeaconData":false,"multiFrameBeacon":false}},{"id":1326,"reading":{"timestamp":1570108410099,"avgRssi":-61.23255813953488,"beaconTypeCode":533,"bluetoothName":"lambda","dataFields":[],"distance":1.0947705454472687,"extraDataFields":[],"id":"b88a6097e2b6","manufacturer":76,"measurementCount":43,"packetCount":10,"rssi":-63,"runningAverageRssi":-61.23255813953488,"serviceUuid":-1,"txPower":-59,"type":"iBeacon","values":["113069EC-6E64-4BD3-6810-DE01B36E8A3E",1,101],"extraBeaconData":false,"multiFrameBeacon":false}},{"id":1327,"reading":{"timestamp":1570108410102,"avgRssi":-61.23255813953488,"beaconTypeCode":533,"bluetoothName":"lambda","dataFields":[],"distance":1.0947705454472687,"extraDataFields":[],"id":"b88a6097e2b6","manufacturer":76,"measurementCount":43,"packetCount":10,"rssi":-63,"runningAverageRssi":-61.23255813953488,"serviceUuid":-1,"txPower":-59,"type":"iBeacon","values":["113069EC-6E64-4BD3-6810-DE01B36E8A3E",1,101],"extraBeaconData":false,"multiFrameBeacon":false}},{"id":1328,"reading":{"timestamp":1570108410122,"avgRssi":-61.23255813953488,"beaconTypeCode":533,"bluetoothName":"lambda","dataFields":[],"distance":1.0947705454472687,"extraDataFields":[],"id":"b88a6097e2b6","manufacturer":76,"measurementCount":43,"packetCount":10,"rssi":-63,"runningAverageRssi":-61.23255813953488,"serviceUuid":-1,"txPower":-59,"type":"iBeacon","values":["113069EC-6E64-4BD3-6810-DE01B36E8A3E",1,101],"extraBeaconData":false,"multiFrameBeacon":false}},{"id":1329,"reading":{"timestamp":1570108411206,"avgRssi":-62.5609756097561,"beaconTypeCode":533,"bluetoothName":"lambda","dataFields":[],"distance":1.1823853367201411,"extraDataFields":[],"id":"b88a6097e2b6","manufacturer":76,"measurementCount":41,"packetCount":8,"rssi":-63,"runningAverageRssi":-62.5609756097561,"serviceUuid":-1,"txPower":-59,"type":"iBeacon","values":["113069EC-6E64-4BD3-6810-DE01B36E8A3E",1,101],"extraBeaconData":false,"multiFrameBeacon":false}},{"id":1330,"reading":{"timestamp":1570108411209,"avgRssi":-62.5609756097561,"beaconTypeCode":533,"bluetoothName":"lambda","dataFields":[],"distance":1.1823853367201411,"extraDataFields":[],"id":"b88a6097e2b6","manufacturer":76,"measurementCount":41,"packetCount":8,"rssi":-63,"runningAverageRssi":-62.5609756097561,"serviceUuid":-1,"txPower":-59,"type":"iBeacon","values":["113069EC-6E64-4BD3-6810-DE01B36E8A3E",1,101],"extraBeaconData":false,"multiFrameBeacon":false}},{"id":1331,"reading":{"timestamp":1570108411211,"avgRssi":-62.5609756097561,"beaconTypeCode":533,"bluetoothName":"lambda","dataFields":[],"distance":1.1823853367201411,"extraDataFields":[],"id":"b88a6097e2b6","manufacturer":76,"measurementCount":41,"packetCount":8,"rssi":-63,"runningAverageRssi":-62.5609756097561,"serviceUuid":-1,"txPower":-59,"type":"iBeacon","values":["113069EC-6E64-4BD3-6810-DE01B36E8A3E",1,101],"extraBeaconData":false,"multiFrameBeacon":false}},{"id":1332,"reading":{"timestamp":1570108412313,"avgRssi":-63.666666666666664,"beaconTypeCode":533,"bluetoothName":"lambda","dataFields":[],"distance":1.2642489251497726,"extraDataFields":[],"id":"b88a6097e2b6","manufacturer":76,"measurementCount":33,"packetCount":1,"rssi":-64,"runningAverageRssi":-63.666666666666664,"serviceUuid":-1,"txPower":-59,"type":"iBeacon","values":["113069EC-6E64-4BD3-6810-DE01B36E8A3E",1,101],"extraBeaconData":false,"multiFrameBeacon":false}},{"id":1333,"reading":{"timestamp":1570108412316,"avgRssi":-63.666666666666664,"beaconTypeCode":533,"bluetoothName":"lambda","dataFields":[],"distance":1.2642489251497726,"extraDataFields":[],"id":"b88a6097e2b6","manufacturer":76,"measurementCount":33,"packetCount":1,"rssi":-64,"runningAverageRssi":-63.666666666666664,"serviceUuid":-1,"txPower":-59,"type":"iBeacon","values":["113069EC-6E64-4BD3-6810-DE01B36E8A3E",1,101],"extraBeaconData":false,"multiFrameBeacon":false}},{"id":1334,"reading":{"timestamp":1570108412318,"avgRssi":-63.666666666666664,"beaconTypeCode":533,"bluetoothName":"lambda","dataFields":[],"distance":1.2642489251497726,"extraDataFields":[],"id":"b88a6097e2b6","manufacturer":76,"measurementCount":33,"packetCount":1,"rssi":-64,"runningAverageRssi":-63.666666666666664,"serviceUuid":-1,"txPower":-59,"type":"iBeacon","values":["113069EC-6E64-4BD3-6810-DE01B36E8A3E",1,101],"extraBeaconData":false,"multiFrameBeacon":false}},{"id":1335,"reading":{"timestamp":1570108415633,"avgRssi":-62.25,"beaconTypeCode":533,"bluetoothName":"lambda","dataFields":[],"distance":1.1608634758181613,"extraDataFields":[],"id":"b88a6097e2b6","manufacturer":76,"measurementCount":8,"packetCount":2,"rssi":-58,"runningAverageRssi":-62.25,"serviceUuid":-1,"txPower":-59,"type":"iBeacon","values":["113069EC-6E64-4BD3-6810-DE01B36E8A3E",1,101],"extraBeaconData":false,"multiFrameBeacon":false}},{"id":1336,"reading":{"timestamp":1570108415636,"avgRssi":-62.25,"beaconTypeCode":533,"bluetoothName":"lambda","dataFields":[],"distance":1.1608634758181613,"extraDataFields":[],"id":"b88a6097e2b6","manufacturer":76,"measurementCount":8,"packetCount":2,"rssi":-58,"runningAverageRssi":-62.25,"serviceUuid":-1,"txPower":-59,"type":"iBeacon","values":["113069EC-6E64-4BD3-6810-DE01B36E8A3E",1,101],"extraBeaconData":false,"multiFrameBeacon":false}},{"id":1337,"reading":{"timestamp":1570108415638,"avgRssi":-62.25,"beaconTypeCode":533,"bluetoothName":"lambda","dataFields":[],"distance":1.1608634758181613,"extraDataFields":[],"id":"b88a6097e2b6","manufacturer":76,"measurementCount":8,"packetCount":2,"rssi":-58,"runningAverageRssi":-62.25,"serviceUuid":-1,"txPower":-59,"type":"iBeacon","values":["113069EC-6E64-4BD3-6810-DE01B36E8A3E",1,101],"extraBeaconData":false,"multiFrameBeacon":false}},{"id":1338,"reading":{"timestamp":1570108416725,"avgRssi":-58.44444444444444,"beaconTypeCode":533,"bluetoothName":"lambda","dataFields":[],"distance":0.9097294011711402,"extraDataFields":[],"id":"b88a6097e2b6","manufacturer":76,"measurementCount":9,"packetCount":7,"rssi":-58,"runningAverageRssi":-58.44444444444444,"serviceUuid":-1,"txPower":-59,"type":"iBeacon","values":["113069EC-6E64-4BD3-6810-DE01B36E8A3E",1,101],"extraBeaconData":false,"multiFrameBeacon":false}},{"id":1339,"reading":{"timestamp":1570108416726,"avgRssi":-58.44444444444444,"beaconTypeCode":533,"bluetoothName":"lambda","dataFields":[],"distance":0.9097294011711402,"extraDataFields":[],"id":"b88a6097e2b6","manufacturer":76,"measurementCount":9,"packetCount":7,"rssi":-58,"runningAverageRssi":-58.44444444444444,"serviceUuid":-1,"txPower":-59,"type":"iBeacon","values":["113069EC-6E64-4BD3-6810-DE01B36E8A3E",1,101],"extraBeaconData":false,"multiFrameBeacon":false}},{"id":1340,"reading":{"timestamp":1570108416726,"avgRssi":-58.44444444444444,"beaconTypeCode":533,"bluetoothName":"lambda","dataFields":[],"distance":0.9097294011711402,"extraDataFields":[],"id":"b88a6097e2b6","manufacturer":76,"measurementCount":9,"packetCount":7,"rssi":-58,"runningAverageRssi":-58.44444444444444,"serviceUuid":-1,"txPower":-59,"type":"iBeacon","values":["113069EC-6E64-4BD3-6810-DE01B36E8A3E",1,101],"extraBeaconData":false,"multiFrameBeacon":false}},{"id":1341,"reading":{"timestamp":1570108417829,"avgRssi":-58.21052631578947,"beaconTypeCode":533,"bluetoothName":"lambda","dataFields":[],"distance":0.8739672198706391,"extraDataFields":[],"id":"b88a6097e2b6","manufacturer":76,"measurementCount":19,"packetCount":10,"rssi":-58,"runningAverageRssi":-58.21052631578947,"serviceUuid":-1,"txPower":-59,"type":"iBeacon","values":["113069EC-6E64-4BD3-6810-DE01B36E8A3E",1,101],"extraBeaconData":false,"multiFrameBeacon":false}},{"id":1342,"reading":{"timestamp":1570108417832,"avgRssi":-58.21052631578947,"beaconTypeCode":533,"bluetoothName":"lambda","dataFields":[],"distance":0.8739672198706391,"extraDataFields":[],"id":"b88a6097e2b6","manufacturer":76,"measurementCount":19,"packetCount":10,"rssi":-58,"runningAverageRssi":-58.21052631578947,"serviceUuid":-1,"txPower":-59,"type":"iBeacon","values":["113069EC-6E64-4BD3-6810-DE01B36E8A3E",1,101],"extraBeaconData":false,"multiFrameBeacon":false}},{"id":1343,"reading":{"timestamp":1570108417833,"avgRssi":-58.21052631578947,"beaconTypeCode":533,"bluetoothName":"lambda","dataFields":[],"distance":0.8739672198706391,"extraDataFields":[],"id":"b88a6097e2b6","manufacturer":76,"measurementCount":19,"packetCount":10,"rssi":-58,"runningAverageRssi":-58.21052631578947,"serviceUuid":-1,"txPower":-59,"type":"iBeacon","values":["113069EC-6E64-4BD3-6810-DE01B36E8A3E",1,101],"extraBeaconData":false,"multiFrameBeacon":false}},{"id":1344,"reading":{"timestamp":1570108418938,"avgRssi":-58.107142857142854,"beaconTypeCode":533,"bluetoothName":"lambda","dataFields":[],"distance":0.8585687943833175,"extraDataFields":[],"id":"b88a6097e2b6","manufacturer":76,"measurementCount":28,"packetCount":9,"rssi":-58,"runningAverageRssi":-58.107142857142854,"serviceUuid":-1,"txPower":-59,"type":"iBeacon","values":["113069EC-6E64-4BD3-6810-DE01B36E8A3E",1,101],"extraBeaconData":false,"multiFrameBeacon":false}},{"id":1345,"reading":{"timestamp":1570108418942,"avgRssi":-58.107142857142854,"beaconTypeCode":533,"bluetoothName":"lambda","dataFields":[],"distance":0.8585687943833175,"extraDataFields":[],"id":"b88a6097e2b6","manufacturer":76,"measurementCount":28,"packetCount":9,"rssi":-58,"runningAverageRssi":-58.107142857142854,"serviceUuid":-1,"txPower":-59,"type":"iBeacon","values":["113069EC-6E64-4BD3-6810-DE01B36E8A3E",1,101],"extraBeaconData":false,"multiFrameBeacon":false}},{"id":1346,"reading":{"timestamp":1570108418944,"avgRssi":-58.107142857142854,"beaconTypeCode":533,"bluetoothName":"lambda","dataFields":[],"distance":0.8585687943833175,"extraDataFields":[],"id":"b88a6097e2b6","manufacturer":76,"measurementCount":28,"packetCount":9,"rssi":-58,"runningAverageRssi":-58.107142857142854,"serviceUuid":-1,"txPower":-59,"type":"iBeacon","values":["113069EC-6E64-4BD3-6810-DE01B36E8A3E",1,101],"extraBeaconData":false,"multiFrameBeacon":false}},{"id":1347,"reading":{"timestamp":1570108420042,"avgRssi":-58.73684210526316,"beaconTypeCode":533,"bluetoothName":"lambda","dataFields":[],"distance":0.9562816452576726,"extraDataFields":[],"id":"b88a6097e2b6","manufacturer":76,"measurementCount":38,"packetCount":10,"rssi":-64,"runningAverageRssi":-58.73684210526316,"serviceUuid":-1,"txPower":-59,"type":"iBeacon","values":["113069EC-6E64-4BD3-6810-DE01B36E8A3E",1,101],"extraBeaconData":false,"multiFrameBeacon":false}},{"id":1348,"reading":{"timestamp":1570108420045,"avgRssi":-58.73684210526316,"beaconTypeCode":533,"bluetoothName":"lambda","dataFields":[],"distance":0.9562816452576726,"extraDataFields":[],"id":"b88a6097e2b6","manufacturer":76,"measurementCount":38,"packetCount":10,"rssi":-64,"runningAverageRssi":-58.73684210526316,"serviceUuid":-1,"txPower":-59,"type":"iBeacon","values":["113069EC-6E64-4BD3-6810-DE01B36E8A3E",1,101],"extraBeaconData":false,"multiFrameBeacon":false}},{"id":1349,"reading":{"timestamp":1570108420047,"avgRssi":-58.73684210526316,"beaconTypeCode":533,"bluetoothName":"lambda","dataFields":[],"distance":0.9562816452576726,"extraDataFields":[],"id":"b88a6097e2b6","manufacturer":76,"measurementCount":38,"packetCount":10,"rssi":-64,"runningAverageRssi":-58.73684210526316,"serviceUuid":-1,"txPower":-59,"type":"iBeacon","values":["113069EC-6E64-4BD3-6810-DE01B36E8A3E",1,101],"extraBeaconData":false,"multiFrameBeacon":false}},{"id":1350,"reading":{"timestamp":1570108421145,"avgRssi":-59.80952380952381,"beaconTypeCode":533,"bluetoothName":"lambda","dataFields":[],"distance":1.0126504613613179,"extraDataFields":[],"id":"b88a6097e2b6","manufacturer":76,"measurementCount":42,"packetCount":8,"rssi":-63,"runningAverageRssi":-59.80952380952381,"serviceUuid":-1,"txPower":-59,"type":"iBeacon","values":["113069EC-6E64-4BD3-6810-DE01B36E8A3E",1,101],"extraBeaconData":false,"multiFrameBeacon":false}},{"id":1351,"reading":{"timestamp":1570108421149,"avgRssi":-59.80952380952381,"beaconTypeCode":533,"bluetoothName":"lambda","dataFields":[],"distance":1.0126504613613179,"extraDataFields":[],"id":"b88a6097e2b6","manufacturer":76,"measurementCount":42,"packetCount":8,"rssi":-63,"runningAverageRssi":-59.80952380952381,"serviceUuid":-1,"txPower":-59,"type":"iBeacon","values":["113069EC-6E64-4BD3-6810-DE01B36E8A3E",1,101],"extraBeaconData":false,"multiFrameBeacon":false}},{"id":1352,"reading":{"timestamp":1570108421150,"avgRssi":-59.80952380952381,"beaconTypeCode":533,"bluetoothName":"lambda","dataFields":[],"distance":1.0126504613613179,"extraDataFields":[],"id":"b88a6097e2b6","manufacturer":76,"measurementCount":42,"packetCount":8,"rssi":-63,"runningAverageRssi":-59.80952380952381,"serviceUuid":-1,"txPower":-59,"type":"iBeacon","values":["113069EC-6E64-4BD3-6810-DE01B36E8A3E",1,101],"extraBeaconData":false,"multiFrameBeacon":false}},{"id":1353,"reading":{"timestamp":1570108422249,"avgRssi":-61.073170731707314,"beaconTypeCode":533,"bluetoothName":"lambda","dataFields":[],"distance":1.084993143691471,"extraDataFields":[],"id":"b88a6097e2b6","manufacturer":76,"measurementCount":41,"packetCount":9,"rssi":-64,"runningAverageRssi":-61.073170731707314,"serviceUuid":-1,"txPower":-59,"type":"iBeacon","values":["113069EC-6E64-4BD3-6810-DE01B36E8A3E",1,101],"extraBeaconData":false,"multiFrameBeacon":false}},{"id":1354,"reading":{"timestamp":1570108422252,"avgRssi":-61.073170731707314,"beaconTypeCode":533,"bluetoothName":"lambda","dataFields":[],"distance":1.084993143691471,"extraDataFields":[],"id":"b88a6097e2b6","manufacturer":76,"measurementCount":41,"packetCount":9,"rssi":-64,"runningAverageRssi":-61.073170731707314,"serviceUuid":-1,"txPower":-59,"type":"iBeacon","values":["113069EC-6E64-4BD3-6810-DE01B36E8A3E",1,101],"extraBeaconData":false,"multiFrameBeacon":false}},{"id":1355,"reading":{"timestamp":1570108422277,"avgRssi":-61.073170731707314,"beaconTypeCode":533,"bluetoothName":"lambda","dataFields":[],"distance":1.084993143691471,"extraDataFields":[],"id":"b88a6097e2b6","manufacturer":76,"measurementCount":41,"packetCount":9,"rssi":-64,"runningAverageRssi":-61.073170731707314,"serviceUuid":-1,"txPower":-59,"type":"iBeacon","values":["113069EC-6E64-4BD3-6810-DE01B36E8A3E",1,101],"extraBeaconData":false,"multiFrameBeacon":false}},{"id":1356,"reading":{"timestamp":1570108423353,"avgRssi":-62.46153846153846,"beaconTypeCode":533,"bluetoothName":"lambda","dataFields":[],"distance":1.1754340622081982,"extraDataFields":[],"id":"b88a6097e2b6","manufacturer":76,"measurementCount":39,"packetCount":7,"rssi":-65,"runningAverageRssi":-62.46153846153846,"serviceUuid":-1,"txPower":-59,"type":"iBeacon","values":["113069EC-6E64-4BD3-6810-DE01B36E8A3E",1,101],"extraBeaconData":false,"multiFrameBeacon":false}},{"id":1357,"reading":{"timestamp":1570108423357,"avgRssi":-62.46153846153846,"beaconTypeCode":533,"bluetoothName":"lambda","dataFields":[],"distance":1.1754340622081982,"extraDataFields":[],"id":"b88a6097e2b6","manufacturer":76,"measurementCount":39,"packetCount":7,"rssi":-65,"runningAverageRssi":-62.46153846153846,"serviceUuid":-1,"txPower":-59,"type":"iBeacon","values":["113069EC-6E64-4BD3-6810-DE01B36E8A3E",1,101],"extraBeaconData":false,"multiFrameBeacon":false}},{"id":1358,"reading":{"timestamp":1570108423358,"avgRssi":-62.46153846153846,"beaconTypeCode":533,"bluetoothName":"lambda","dataFields":[],"distance":1.1754340622081982,"extraDataFields":[],"id":"b88a6097e2b6","manufacturer":76,"measurementCount":39,"packetCount":7,"rssi":-65,"runningAverageRssi":-62.46153846153846,"serviceUuid":-1,"txPower":-59,"type":"iBeacon","values":["113069EC-6E64-4BD3-6810-DE01B36E8A3E",1,101],"extraBeaconData":false,"multiFrameBeacon":false}},{"id":1359,"reading":{"timestamp":1570108424454,"avgRssi":-62.83783783783784,"beaconTypeCode":533,"bluetoothName":"lambda","dataFields":[],"distance":1.2020891973463743,"extraDataFields":[],"id":"b88a6097e2b6","manufacturer":76,"measurementCount":37,"packetCount":8,"rssi":-57,"runningAverageRssi":-62.83783783783784,"serviceUuid":-1,"txPower":-59,"type":"iBeacon","values":["113069EC-6E64-4BD3-6810-DE01B36E8A3E",1,101],"extraBeaconData":false,"multiFrameBeacon":false}},{"id":1360,"reading":{"timestamp":1570108424456,"avgRssi":-62.83783783783784,"beaconTypeCode":533,"bluetoothName":"lambda","dataFields":[],"distance":1.2020891973463743,"extraDataFields":[],"id":"b88a6097e2b6","manufacturer":76,"measurementCount":37,"packetCount":8,"rssi":-57,"runningAverageRssi":-62.83783783783784,"serviceUuid":-1,"txPower":-59,"type":"iBeacon","values":["113069EC-6E64-4BD3-6810-DE01B36E8A3E",1,101],"extraBeaconData":false,"multiFrameBeacon":false}},{"id":1361,"reading":{"timestamp":1570108424486,"avgRssi":-62.83783783783784,"beaconTypeCode":533,"bluetoothName":"lambda","dataFields":[],"distance":1.2020891973463743,"extraDataFields":[],"id":"b88a6097e2b6","manufacturer":76,"measurementCount":37,"packetCount":8,"rssi":-57,"runningAverageRssi":-62.83783783783784,"serviceUuid":-1,"txPower":-59,"type":"iBeacon","values":["113069EC-6E64-4BD3-6810-DE01B36E8A3E",1,101],"extraBeaconData":false,"multiFrameBeacon":false}},{"id":1362,"reading":{"timestamp":1570108425554,"avgRssi":-61.333333333333336,"beaconTypeCode":533,"bluetoothName":"lambda","dataFields":[],"distance":1.1010310528176195,"extraDataFields":[],"id":"b88a6097e2b6","manufacturer":76,"measurementCount":36,"packetCount":9,"rssi":-58,"runningAverageRssi":-61.333333333333336,"serviceUuid":-1,"txPower":-59,"type":"iBeacon","values":["113069EC-6E64-4BD3-6810-DE01B36E8A3E",1,101],"extraBeaconData":false,"multiFrameBeacon":false}},{"id":1363,"reading":{"timestamp":1570108425556,"avgRssi":-61.333333333333336,"beaconTypeCode":533,"bluetoothName":"lambda","dataFields":[],"distance":1.1010310528176195,"extraDataFields":[],"id":"b88a6097e2b6","manufacturer":76,"measurementCount":36,"packetCount":9,"rssi":-58,"runningAverageRssi":-61.333333333333336,"serviceUuid":-1,"txPower":-59,"type":"iBeacon","values":["113069EC-6E64-4BD3-6810-DE01B36E8A3E",1,101],"extraBeaconData":false,"multiFrameBeacon":false}},{"id":1364,"reading":{"timestamp":1570108425557,"avgRssi":-61.333333333333336,"beaconTypeCode":533,"bluetoothName":"lambda","dataFields":[],"distance":1.1010310528176195,"extraDataFields":[],"id":"b88a6097e2b6","manufacturer":76,"measurementCount":36,"packetCount":9,"rssi":-58,"runningAverageRssi":-61.333333333333336,"serviceUuid":-1,"txPower":-59,"type":"iBeacon","values":["113069EC-6E64-4BD3-6810-DE01B36E8A3E",1,101],"extraBeaconData":false,"multiFrameBeacon":false}},{"id":1365,"reading":{"timestamp":1570108426661,"avgRssi":-59.81578947368421,"beaconTypeCode":533,"bluetoothName":"lambda","dataFields":[],"distance":1.0129873566715775,"extraDataFields":[],"id":"b88a6097e2b6","manufacturer":76,"measurementCount":38,"packetCount":9,"rssi":-56,"runningAverageRssi":-59.81578947368421,"serviceUuid":-1,"txPower":-59,"type":"iBeacon","values":["113069EC-6E64-4BD3-6810-DE01B36E8A3E",1,101],"extraBeaconData":false,"multiFrameBeacon":false}},{"id":1366,"reading":{"timestamp":1570108426664,"avgRssi":-59.81578947368421,"beaconTypeCode":533,"bluetoothName":"lambda","dataFields":[],"distance":1.0129873566715775,"extraDataFields":[],"id":"b88a6097e2b6","manufacturer":76,"measurementCount":38,"packetCount":9,"rssi":-56,"runningAverageRssi":-59.81578947368421,"serviceUuid":-1,"txPower":-59,"type":"iBeacon","values":["113069EC-6E64-4BD3-6810-DE01B36E8A3E",1,101],"extraBeaconData":false,"multiFrameBeacon":false}},{"id":1367,"reading":{"timestamp":1570108426666,"avgRssi":-59.81578947368421,"beaconTypeCode":533,"bluetoothName":"lambda","dataFields":[],"distance":1.0129873566715775,"extraDataFields":[],"id":"b88a6097e2b6","manufacturer":76,"measurementCount":38,"packetCount":9,"rssi":-56,"runningAverageRssi":-59.81578947368421,"serviceUuid":-1,"txPower":-59,"type":"iBeacon","values":["113069EC-6E64-4BD3-6810-DE01B36E8A3E",1,101],"extraBeaconData":false,"multiFrameBeacon":false}},{"id":1368,"reading":{"timestamp":1570108427762,"avgRssi":-58.35897435897436,"beaconTypeCode":533,"bluetoothName":"lambda","dataFields":[],"distance":0.8965125851961313,"extraDataFields":[],"id":"b88a6097e2b6","manufacturer":76,"measurementCount":39,"packetCount":9,"rssi":-58,"runningAverageRssi":-58.35897435897436,"serviceUuid":-1,"txPower":-59,"type":"iBeacon","values":["113069EC-6E64-4BD3-6810-DE01B36E8A3E",1,101],"extraBeaconData":false,"multiFrameBeacon":false}},{"id":1369,"reading":{"timestamp":1570108427764,"avgRssi":-58.35897435897436,"beaconTypeCode":533,"bluetoothName":"lambda","dataFields":[],"distance":0.8965125851961313,"extraDataFields":[],"id":"b88a6097e2b6","manufacturer":76,"measurementCount":39,"packetCount":9,"rssi":-58,"runningAverageRssi":-58.35897435897436,"serviceUuid":-1,"txPower":-59,"type":"iBeacon","values":["113069EC-6E64-4BD3-6810-DE01B36E8A3E",1,101],"extraBeaconData":false,"multiFrameBeacon":false}},{"id":1370,"reading":{"timestamp":1570108427794,"avgRssi":-58.35897435897436,"beaconTypeCode":533,"bluetoothName":"lambda","dataFields":[],"distance":0.8965125851961313,"extraDataFields":[],"id":"b88a6097e2b6","manufacturer":76,"measurementCount":39,"packetCount":9,"rssi":-58,"runningAverageRssi":-58.35897435897436,"serviceUuid":-1,"txPower":-59,"type":"iBeacon","values":["113069EC-6E64-4BD3-6810-DE01B36E8A3E",1,101],"extraBeaconData":false,"multiFrameBeacon":false}},{"id":1371,"reading":{"timestamp":1570108428867,"avgRssi":-57.292682926829265,"beaconTypeCode":533,"bluetoothName":"lambda","dataFields":[],"distance":0.745540918088841,"extraDataFields":[],"id":"b88a6097e2b6","manufacturer":76,"measurementCount":41,"packetCount":11,"rssi":-57,"runningAverageRssi":-57.292682926829265,"serviceUuid":-1,"txPower":-59,"type":"iBeacon","values":["113069EC-6E64-4BD3-6810-DE01B36E8A3E",1,101],"extraBeaconData":false,"multiFrameBeacon":false}},{"id":1372,"reading":{"timestamp":1570108428870,"avgRssi":-57.292682926829265,"beaconTypeCode":533,"bluetoothName":"lambda","dataFields":[],"distance":0.745540918088841,"extraDataFields":[],"id":"b88a6097e2b6","manufacturer":76,"measurementCount":41,"packetCount":11,"rssi":-57,"runningAverageRssi":-57.292682926829265,"serviceUuid":-1,"txPower":-59,"type":"iBeacon","values":["113069EC-6E64-4BD3-6810-DE01B36E8A3E",1,101],"extraBeaconData":false,"multiFrameBeacon":false}},{"id":1373,"reading":{"timestamp":1570108428872,"avgRssi":-57.292682926829265,"beaconTypeCode":533,"bluetoothName":"lambda","dataFields":[],"distance":0.745540918088841,"extraDataFields":[],"id":"b88a6097e2b6","manufacturer":76,"measurementCount":41,"packetCount":11,"rssi":-57,"runningAverageRssi":-57.292682926829265,"serviceUuid":-1,"txPower":-59,"type":"iBeacon","values":["113069EC-6E64-4BD3-6810-DE01B36E8A3E",1,101],"extraBeaconData":false,"multiFrameBeacon":false}},{"id":1374,"reading":{"timestamp":1570108429973,"avgRssi":-57.3,"beaconTypeCode":533,"bluetoothName":"lambda","dataFields":[],"distance":0.7464936250311629,"extraDataFields":[],"id":"b88a6097e2b6","manufacturer":76,"measurementCount":40,"packetCount":7,"rssi":-56,"runningAverageRssi":-57.3,"serviceUuid":-1,"txPower":-59,"type":"iBeacon","values":["113069EC-6E64-4BD3-6810-DE01B36E8A3E",1,101],"extraBeaconData":false,"multiFrameBeacon":false}},{"id":1375,"reading":{"timestamp":1570108429976,"avgRssi":-57.3,"beaconTypeCode":533,"bluetoothName":"lambda","dataFields":[],"distance":0.7464936250311629,"extraDataFields":[],"id":"b88a6097e2b6","manufacturer":76,"measurementCount":40,"packetCount":7,"rssi":-56,"runningAverageRssi":-57.3,"serviceUuid":-1,"txPower":-59,"type":"iBeacon","values":["113069EC-6E64-4BD3-6810-DE01B36E8A3E",1,101],"extraBeaconData":false,"multiFrameBeacon":false}},{"id":1376,"reading":{"timestamp":1570108429978,"avgRssi":-57.3,"beaconTypeCode":533,"bluetoothName":"lambda","dataFields":[],"distance":0.7464936250311629,"extraDataFields":[],"id":"b88a6097e2b6","manufacturer":76,"measurementCount":40,"packetCount":7,"rssi":-56,"runningAverageRssi":-57.3,"serviceUuid":-1,"txPower":-59,"type":"iBeacon","values":["113069EC-6E64-4BD3-6810-DE01B36E8A3E",1,101],"extraBeaconData":false,"multiFrameBeacon":false}},{"id":1377,"reading":{"timestamp":1570108431077,"avgRssi":-57.214285714285715,"beaconTypeCode":533,"bluetoothName":"lambda","dataFields":[],"distance":0.7354017984881859,"extraDataFields":[],"id":"b88a6097e2b6","manufacturer":76,"measurementCount":42,"packetCount":10,"rssi":-58,"runningAverageRssi":-57.214285714285715,"serviceUuid":-1,"txPower":-59,"type":"iBeacon","values":["113069EC-6E64-4BD3-6810-DE01B36E8A3E",1,101],"extraBeaconData":false,"multiFrameBeacon":false}},{"id":1378,"reading":{"timestamp":1570108431080,"avgRssi":-57.214285714285715,"beaconTypeCode":533,"bluetoothName":"lambda","dataFields":[],"distance":0.7354017984881859,"extraDataFields":[],"id":"b88a6097e2b6","manufacturer":76,"measurementCount":42,"packetCount":10,"rssi":-58,"runningAverageRssi":-57.214285714285715,"serviceUuid":-1,"txPower":-59,"type":"iBeacon","values":["113069EC-6E64-4BD3-6810-DE01B36E8A3E",1,101],"extraBeaconData":false,"multiFrameBeacon":false}},{"id":1379,"reading":{"timestamp":1570108431082,"avgRssi":-57.214285714285715,"beaconTypeCode":533,"bluetoothName":"lambda","dataFields":[],"distance":0.7354017984881859,"extraDataFields":[],"id":"b88a6097e2b6","manufacturer":76,"measurementCount":42,"packetCount":10,"rssi":-58,"runningAverageRssi":-57.214285714285715,"serviceUuid":-1,"txPower":-59,"type":"iBeacon","values":["113069EC-6E64-4BD3-6810-DE01B36E8A3E",1,101],"extraBeaconData":false,"multiFrameBeacon":false}},{"id":1380,"reading":{"timestamp":1570108432188,"avgRssi":-57.30769230769231,"beaconTypeCode":533,"bluetoothName":"lambda","dataFields":[],"distance":0.7474963700294595,"extraDataFields":[],"id":"b88a6097e2b6","manufacturer":76,"measurementCount":39,"packetCount":7,"rssi":-56,"runningAverageRssi":-57.30769230769231,"serviceUuid":-1,"txPower":-59,"type":"iBeacon","values":["113069EC-6E64-4BD3-6810-DE01B36E8A3E",1,101],"extraBeaconData":false,"multiFrameBeacon":false}},{"id":1381,"reading":{"timestamp":1570108432191,"avgRssi":-57.30769230769231,"beaconTypeCode":533,"bluetoothName":"lambda","dataFields":[],"distance":0.7474963700294595,"extraDataFields":[],"id":"b88a6097e2b6","manufacturer":76,"measurementCount":39,"packetCount":7,"rssi":-56,"runningAverageRssi":-57.30769230769231,"serviceUuid":-1,"txPower":-59,"type":"iBeacon","values":["113069EC-6E64-4BD3-6810-DE01B36E8A3E",1,101],"extraBeaconData":false,"multiFrameBeacon":false}},{"id":1382,"reading":{"timestamp":1570108432193,"avgRssi":-57.30769230769231,"beaconTypeCode":533,"bluetoothName":"lambda","dataFields":[],"distance":0.7474963700294595,"extraDataFields":[],"id":"b88a6097e2b6","manufacturer":76,"measurementCount":39,"packetCount":7,"rssi":-56,"runningAverageRssi":-57.30769230769231,"serviceUuid":-1,"txPower":-59,"type":"iBeacon","values":["113069EC-6E64-4BD3-6810-DE01B36E8A3E",1,101],"extraBeaconData":false,"multiFrameBeacon":false}},{"id":1383,"reading":{"timestamp":1570108436611,"avgRssi":-56.714285714285715,"beaconTypeCode":533,"bluetoothName":"lambda","dataFields":[],"distance":0.6736038350283031,"extraDataFields":[],"id":"b88a6097e2b6","manufacturer":76,"measurementCount":7,"packetCount":5,"rssi":-56,"runningAverageRssi":-56.714285714285715,"serviceUuid":-1,"txPower":-59,"type":"iBeacon","values":["113069EC-6E64-4BD3-6810-DE01B36E8A3E",1,101],"extraBeaconData":false,"multiFrameBeacon":false}},{"id":1384,"reading":{"timestamp":1570108436614,"avgRssi":-56.714285714285715,"beaconTypeCode":533,"bluetoothName":"lambda","dataFields":[],"distance":0.6736038350283031,"extraDataFields":[],"id":"b88a6097e2b6","manufacturer":76,"measurementCount":7,"packetCount":5,"rssi":-56,"runningAverageRssi":-56.714285714285715,"serviceUuid":-1,"txPower":-59,"type":"iBeacon","values":["113069EC-6E64-4BD3-6810-DE01B36E8A3E",1,101],"extraBeaconData":false,"multiFrameBeacon":false}},{"id":1385,"reading":{"timestamp":1570108436616,"avgRssi":-56.714285714285715,"beaconTypeCode":533,"bluetoothName":"lambda","dataFields":[],"distance":0.6736038350283031,"extraDataFields":[],"id":"b88a6097e2b6","manufacturer":76,"measurementCount":7,"packetCount":5,"rssi":-56,"runningAverageRssi":-56.714285714285715,"serviceUuid":-1,"txPower":-59,"type":"iBeacon","values":["113069EC-6E64-4BD3-6810-DE01B36E8A3E",1,101],"extraBeaconData":false,"multiFrameBeacon":false}},{"id":1386,"reading":{"timestamp":1570108437716,"avgRssi":-56.92857142857143,"beaconTypeCode":533,"bluetoothName":"lambda","dataFields":[],"distance":0.6994919820754483,"extraDataFields":[],"id":"b88a6097e2b6","manufacturer":76,"measurementCount":14,"packetCount":9,"rssi":-58,"runningAverageRssi":-56.92857142857143,"serviceUuid":-1,"txPower":-59,"type":"iBeacon","values":["113069EC-6E64-4BD3-6810-DE01B36E8A3E",1,101],"extraBeaconData":false,"multiFrameBeacon":false}},{"id":1387,"reading":{"timestamp":1570108437719,"avgRssi":-56.92857142857143,"beaconTypeCode":533,"bluetoothName":"lambda","dataFields":[],"distance":0.6994919820754483,"extraDataFields":[],"id":"b88a6097e2b6","manufacturer":76,"measurementCount":14,"packetCount":9,"rssi":-58,"runningAverageRssi":-56.92857142857143,"serviceUuid":-1,"txPower":-59,"type":"iBeacon","values":["113069EC-6E64-4BD3-6810-DE01B36E8A3E",1,101],"extraBeaconData":false,"multiFrameBeacon":false}},{"id":1388,"reading":{"timestamp":1570108437721,"avgRssi":-56.92857142857143,"beaconTypeCode":533,"bluetoothName":"lambda","dataFields":[],"distance":0.6994919820754483,"extraDataFields":[],"id":"b88a6097e2b6","manufacturer":76,"measurementCount":14,"packetCount":9,"rssi":-58,"runningAverageRssi":-56.92857142857143,"serviceUuid":-1,"txPower":-59,"type":"iBeacon","values":["113069EC-6E64-4BD3-6810-DE01B36E8A3E",1,101],"extraBeaconData":false,"multiFrameBeacon":false}},{"id":1389,"reading":{"timestamp":1570108438821,"avgRssi":-57.22727272727273,"beaconTypeCode":533,"bluetoothName":"lambda","dataFields":[],"distance":0.7370727857310957,"extraDataFields":[],"id":"b88a6097e2b6","manufacturer":76,"measurementCount":22,"packetCount":8,"rssi":-58,"runningAverageRssi":-57.22727272727273,"serviceUuid":-1,"txPower":-59,"type":"iBeacon","values":["113069EC-6E64-4BD3-6810-DE01B36E8A3E",1,101],"extraBeaconData":false,"multiFrameBeacon":false}},{"id":1390,"reading":{"timestamp":1570108438825,"avgRssi":-57.22727272727273,"beaconTypeCode":533,"bluetoothName":"lambda","dataFields":[],"distance":0.7370727857310957,"extraDataFields":[],"id":"b88a6097e2b6","manufacturer":76,"measurementCount":22,"packetCount":8,"rssi":-58,"runningAverageRssi":-57.22727272727273,"serviceUuid":-1,"txPower":-59,"type":"iBeacon","values":["113069EC-6E64-4BD3-6810-DE01B36E8A3E",1,101],"extraBeaconData":false,"multiFrameBeacon":false}},{"id":1391,"reading":{"timestamp":1570108438827,"avgRssi":-57.22727272727273,"beaconTypeCode":533,"bluetoothName":"lambda","dataFields":[],"distance":0.7370727857310957,"extraDataFields":[],"id":"b88a6097e2b6","manufacturer":76,"measurementCount":22,"packetCount":8,"rssi":-58,"runningAverageRssi":-57.22727272727273,"serviceUuid":-1,"txPower":-59,"type":"iBeacon","values":["113069EC-6E64-4BD3-6810-DE01B36E8A3E",1,101],"extraBeaconData":false,"multiFrameBeacon":false}},{"id":1392,"reading":{"timestamp":1570108439929,"avgRssi":-57.193548387096776,"beaconTypeCode":533,"bluetoothName":"lambda","dataFields":[],"distance":0.7327406767128587,"extraDataFields":[],"id":"b88a6097e2b6","manufacturer":76,"measurementCount":31,"packetCount":9,"rssi":-57,"runningAverageRssi":-57.193548387096776,"serviceUuid":-1,"txPower":-59,"type":"iBeacon","values":["113069EC-6E64-4BD3-6810-DE01B36E8A3E",1,101],"extraBeaconData":false,"multiFrameBeacon":false}},{"id":1393,"reading":{"timestamp":1570108439932,"avgRssi":-57.193548387096776,"beaconTypeCode":533,"bluetoothName":"lambda","dataFields":[],"distance":0.7327406767128587,"extraDataFields":[],"id":"b88a6097e2b6","manufacturer":76,"measurementCount":31,"packetCount":9,"rssi":-57,"runningAverageRssi":-57.193548387096776,"serviceUuid":-1,"txPower":-59,"type":"iBeacon","values":["113069EC-6E64-4BD3-6810-DE01B36E8A3E",1,101],"extraBeaconData":false,"multiFrameBeacon":false}},{"id":1394,"reading":{"timestamp":1570108439934,"avgRssi":-57.193548387096776,"beaconTypeCode":533,"bluetoothName":"lambda","dataFields":[],"distance":0.7327406767128587,"extraDataFields":[],"id":"b88a6097e2b6","manufacturer":76,"measurementCount":31,"packetCount":9,"rssi":-57,"runningAverageRssi":-57.193548387096776,"serviceUuid":-1,"txPower":-59,"type":"iBeacon","values":["113069EC-6E64-4BD3-6810-DE01B36E8A3E",1,101],"extraBeaconData":false,"multiFrameBeacon":false}},{"id":1395,"reading":{"timestamp":1570108441033,"avgRssi":-57.44736842105263,"beaconTypeCode":533,"bluetoothName":"lambda","dataFields":[],"distance":0.7659162336101644,"extraDataFields":[],"id":"b88a6097e2b6","manufacturer":76,"measurementCount":38,"packetCount":8,"rssi":-60,"runningAverageRssi":-57.44736842105263,"serviceUuid":-1,"txPower":-59,"type":"iBeacon","values":["113069EC-6E64-4BD3-6810-DE01B36E8A3E",1,101],"extraBeaconData":false,"multiFrameBeacon":false}},{"id":1396,"reading":{"timestamp":1570108441036,"avgRssi":-57.44736842105263,"beaconTypeCode":533,"bluetoothName":"lambda","dataFields":[],"distance":0.7659162336101644,"extraDataFields":[],"id":"b88a6097e2b6","manufacturer":76,"measurementCount":38,"packetCount":8,"rssi":-60,"runningAverageRssi":-57.44736842105263,"serviceUuid":-1,"txPower":-59,"type":"iBeacon","values":["113069EC-6E64-4BD3-6810-DE01B36E8A3E",1,101],"extraBeaconData":false,"multiFrameBeacon":false}},{"id":1397,"reading":{"timestamp":1570108441038,"avgRssi":-57.44736842105263,"beaconTypeCode":533,"bluetoothName":"lambda","dataFields":[],"distance":0.7659162336101644,"extraDataFields":[],"id":"b88a6097e2b6","manufacturer":76,"measurementCount":38,"packetCount":8,"rssi":-60,"runningAverageRssi":-57.44736842105263,"serviceUuid":-1,"txPower":-59,"type":"iBeacon","values":["113069EC-6E64-4BD3-6810-DE01B36E8A3E",1,101],"extraBeaconData":false,"multiFrameBeacon":false}}]}}